[
    {
        "name": "José Lara",
        "race": "español",
        "gender": "M",
        "father": " ",
        "mother": " ",
        "spouse": " ",
        "age": 50
    },
    {
        "name": "María Antonia Campos",
        "race": "india ladina",
        "gender": "F",
        "father": " ",
        "mother": " ",
        "spouse": "José Lara",
        "age": 23
    },
    {
        "name": "José Julián Lara",
        "race": "español; india ladina",
        "gender": "M",
        "father": "José Lara",
        "mother": "María Antonia Campos",
        "spouse": " ",
        "age": 4
    },
    {
        "name": "Juana Jesús Lara",
        "race": "español; india ladina",
        "gender": "F",
        "father": "José Lara",
        "mother": "María Antonia Campos",
        "spouse": " ",
        "age": 6
    },
    {
        "name": "María Faustina Lara",
        "race": "español; india ladina",
        "gender": "F",
        "father": "José Lara",
        "mother": "María Antonia Campos",
        "spouse": " ",
        "age": 2
    },
    {
        "name": "José Antonio Navarro",
        "race": "mestizo",
        "gender": "M",
        "father": " ",
        "mother": " ",
        "spouse": " ",
        "age": 42
    },
    {
        "name": "María Rufina Dorotea",
        "race": "mulata",
        "gender": "F",
        "father": " ",
        "mother": " ",
        "spouse": "José Antonio Navarro",
        "age": null
    },
    {
        "name": "José María Navarro",
        "race": "mestizo; mulata",
        "gender": "M",
        "father": "José Antonio Navarro",
        "mother": "María Rufina Dorotea",
        "spouse": " ",
        "age": 10
    },
    {
        "name": "José Clemente Navarro",
        "race": "mestizo; mulata",
        "gender": "M",
        "father": "José Antonio Navarro",
        "mother": "María Rufina Dorotea",
        "spouse": " ",
        "age": 9
    },
    {
        "name": "María Josefa Navarro",
        "race": "mestizo; mulata",
        "gender": "F",
        "father": "José Antonio Navarro",
        "mother": "María Rufina Dorotea",
        "spouse": " ",
        "age": 4
    },
    {
        "name": "Basilio Rosas",
        "race": "indio",
        "gender": "M",
        "father": " ",
        "mother": " ",
        "spouse": " ",
        "age": 67
    },
    {
        "name": "María Manuela Calixtra Hernández",
        "race": "mulata",
        "gender": "F",
        "father": " ",
        "mother": " ",
        "spouse": "Basilio Rosas",
        "age": null
    },
    {
        "name": "José Máximo Rosas",
        "race": "indio; mulata",
        "gender": "M",
        "father": "Basilio Rosas",
        "mother": "María Manuela Calixtra Hernández",
        "spouse": " ",
        "age": 15
    },
    {
        "name": "Carlos Rosas",
        "race": "indio; mulata",
        "gender": "M",
        "father": "Basilio Rosas",
        "mother": "María Manuela Calixtra Hernández",
        "spouse": " ",
        "age": 12
    },
    {
        "name": "Antonio Rosalino Rosas",
        "race": "indio; mulata",
        "gender": "M",
        "father": "Basilio Rosas",
        "mother": "María Manuela Calixtra Hernández",
        "spouse": " ",
        "age": 7
    },
    {
        "name": "José Marcelino Rosas",
        "race": "indio; mulata",
        "gender": "M",
        "father": "Basilio Rosas",
        "mother": "María Manuela Calixtra Hernández",
        "spouse": " ",
        "age": 4
    },
    {
        "name": "Juan Estaban Rosas",
        "race": "indio; mulata",
        "gender": "M",
        "father": "Basilio Rosas",
        "mother": "María Manuela Calixtra Hernández",
        "spouse": " ",
        "age": 2
    },
    {
        "name": "María Josefa Rosas",
        "race": "indio; mulata",
        "gender": "F",
        "father": "Basilio Rosas",
        "mother": "María Manuela Calixtra Hernández",
        "spouse": " ",
        "age": 8
    },
    {
        "name": "Antonio Mesa",
        "race": "negro",
        "gender": "M",
        "father": " ",
        "mother": " ",
        "spouse": " ",
        "age": 38
    },
    {
        "name": "Ana Gertrudis López",
        "race": "mulata",
        "gender": "F",
        "father": " ",
        "mother": " ",
        "spouse": "Antonio Mesa",
        "age": 27
    },
    {
        "name": "Antonio María Mesa",
        "race": "negro; mulata",
        "gender": "M",
        "father": "Antonio Mesa",
        "mother": "Ana Gertrudis López",
        "spouse": " ",
        "age": 8
    },
    {
        "name": "María Paula Mesa",
        "race": "negro; mulata",
        "gender": "F",
        "father": "Antonio Mesa",
        "mother": "Ana Gertrudis López",
        "spouse": " ",
        "age": 10
    },
    {
        "name": "Antonio Villavicencio",
        "race": "español",
        "gender": "M",
        "father": " ",
        "mother": " ",
        "spouse": " ",
        "age": 30
    },
    {
        "name": "María de los Santos Seferina",
        "race": "india",
        "gender": "F",
        "father": " ",
        "mother": " ",
        "spouse": "Antonio Villavicencio",
        "age": 26
    },
    {
        "name": "María Antonia Josefa ",
        "race": "india",
        "gender": "F",
        "father": " ",
        "mother": "María de los Santos Seferina",
        "spouse": " ",
        "age": 8
    },
    {
        "name": "José Vanegas",
        "race": "indio",
        "gender": "M",
        "father": " ",
        "mother": " ",
        "spouse": " ",
        "age": 28
    },
    {
        "name": "María Máxima Aguilar",
        "race": "india",
        "gender": "F",
        "father": " ",
        "mother": " ",
        "spouse": "José Vanegas",
        "age": 20
    },
    {
        "name": "Cosmé Damién Vanegas",
        "race": "indio; india",
        "gender": "M",
        "father": "José Vanegas",
        "mother": "María Máxima Aguilar",
        "spouse": " ",
        "age": 1
    },
    {
        "name": "Alejandro Rosas",
        "race": "indio",
        "gender": "M",
        "father": " ",
        "mother": " ",
        "spouse": " ",
        "age": 19
    },
    {
        "name": "Juana Rodríguez",
        "race": "coyota",
        "gender": "F",
        "father": " ",
        "mother": " ",
        "spouse": "Alejandro Rosas",
        "age": 20
    },
    {
        "name": "Pablo Rodríguez",
        "race": "indio",
        "gender": "M",
        "father": " ",
        "mother": " ",
        "spouse": " ",
        "age": 25
    },
    {
        "name": "María Rosalía Noriega",
        "race": "india",
        "gender": "F",
        "father": " ",
        "mother": " ",
        "spouse": "Pablo Rodríguez",
        "age": 26
    },
    {
        "name": "María Antonia Rodríguez",
        "race": "indio; india",
        "gender": "F",
        "father": "Pablo Rodríguez",
        "mother": "María Rosalía Noriega",
        "spouse": " ",
        "age": 1
    },
    {
        "name": "Manuel Camero",
        "race": "mulato",
        "gender": "M",
        "father": " ",
        "mother": " ",
        "spouse": " ",
        "age": 30
    },
    {
        "name": "María Tomasa ",
        "race": "mulata",
        "gender": "F",
        "father": " ",
        "mother": " ",
        "spouse": "Manuel Camero",
        "age": 24
    },
    {
        "name": "Luís Quintero",
        "race": "negro",
        "gender": "M",
        "father": " ",
        "mother": " ",
        "spouse": " ",
        "age": 55
    },
    {
        "name": "María Petra Rubio",
        "race": "mulata",
        "gender": "F",
        "father": " ",
        "mother": " ",
        "spouse": "Luís Quintero",
        "age": 40
    },
    {
        "name": "José Clemente Quintero",
        "race": "negro; mulata",
        "gender": "M",
        "father": "Luís Quintero",
        "mother": "María Petra Rubio",
        "spouse": " ",
        "age": 3
    },
    {
        "name": "María Gertrudis Quintero",
        "race": "negro; mulata",
        "gender": "F",
        "father": "Luís Quintero",
        "mother": "María Petra Rubio",
        "spouse": " ",
        "age": 16
    },
    {
        "name": "María Concepción Quintero",
        "race": "negro; mulata",
        "gender": "F",
        "father": "Luís Quintero",
        "mother": "María Petra Rubio",
        "spouse": " ",
        "age": 9
    },
    {
        "name": "Tomasa Quintero",
        "race": "negro; mulata",
        "gender": "F",
        "father": "Luís Quintero",
        "mother": "María Petra Rubio",
        "spouse": " ",
        "age": 7
    },
    {
        "name": "Rafaela Quintero",
        "race": "negro; mulata",
        "gender": "F",
        "father": "Luís Quintero",
        "mother": "María Petra Rubio",
        "spouse": " ",
        "age": 6
    },
    {
        "name": "José Moreno",
        "race": "mulato",
        "gender": "M",
        "father": " ",
        "mother": " ",
        "spouse": " ",
        "age": 22
    },
    {
        "name": "María Guadalupe Gertrudis",
        "race": "mulata",
        "gender": "F",
        "father": " ",
        "mother": " ",
        "spouse": "José Moreno",
        "age": 19
    },
    {
        "name": "Antonio Miranda",
        "race": "chino",
        "gender": "M",
        "father": " ",
        "mother": " ",
        "spouse": " ",
        "age": 50
    },
    {
        "name": "Juana María Miranda",
        "race": "chino",
        "gender": "F",
        "father": "Antonio Miranda",
        "mother": " ",
        "spouse": " ",
        "age": 11
    }
]